matplothelp/__init__.py
matplothelp/aff.py
matplothelp/base.py
matplothelp/boxplot.py
matplothelp/cae.py
matplothelp/google.py
matplothelp/host.py
matplothelp/label.py
matplothelp/line.py
matplothelp/max.py
matplothelp/mean.py
matplothelp/mono.py
matplothelp/reverse.py
matplothelp/rsa.py
matplothelp/sniffer.py
matplothelp/students.py
matplothelp/tabular.py
matplothelp/vig.py
matplothelp-0.0.1.dist-info/LICENSE
matplothelp-0.0.1.dist-info/METADATA
matplothelp-0.0.1.dist-info/WHEEL
matplothelp-0.0.1.dist-info/top_level.txt
matplothelp-0.0.1.dist-info/RECORD
